ctxflow/.env.dev
ctxflow/__about__.py
ctxflow/__init__.py
ctxflow/__main__.py
ctxflow/base.py
ctxflow/browsr.css
ctxflow/browsr.py
ctxflow/cli.py
ctxflow/config.py
ctxflow/exceptions.py
ctxflow/logger.py
ctxflow/runner.py
ctxflow/utils.py
ctxflow/.ctxflow/settings.json
ctxflow/claude/settings.json
ctxflow/claude/commands/prime.md
ctxflow/claude/commands/web-builder.md
ctxflow/claude/hooks/notification.py
ctxflow/claude/hooks/post_tool_use.py
ctxflow/claude/hooks/pre_tool_use.py
ctxflow/claude/hooks/stop.py
ctxflow/claude/hooks/subagent_stop.py
ctxflow/claude/hooks/utils/llm/anth.py
ctxflow/claude/hooks/utils/llm/oai.py
ctxflow/claude/hooks/utils/tts/elevenlabs_tts.py
ctxflow/prompts/template_prime.xml
ctxflow/prompts/Prompts/.git
ctxflow/prompts/Prompts/BTY_SEO_BRANDING_PROMPT.md
ctxflow/prompts/Prompts/UPDATE_TEMPLATE_JSON_PROMPT.md
ctxflow/prompts/Prompts/WATERMARK_PROMPT.md
ctxflow/prompts/Prompts/web-builder.md
ctxflow/prompts/agentic/CtxPrime.md
ctxflow/prompts/protocol/SharedProtocol.md
ctxflow/prompts/user/web_builder.xml
ctxflow/screens/__init__.py
ctxflow/screens/code_browser.py
ctxflow/scripts/prgs.sh
ctxflow/scripts/template-processor.sh
ctxflow/widgets/__init__.py
ctxflow/widgets/code_browser.py
ctxflow/widgets/confirmation.py
ctxflow/widgets/double_click_directory_tree.py
ctxflow/widgets/files.py
ctxflow/widgets/universal_directory_tree.py
ctxflow/widgets/vim.py
ctxflow/widgets/windows.py
ctxflow-1.5.dist-info/METADATA
ctxflow-1.5.dist-info/WHEEL
ctxflow-1.5.dist-info/entry_points.txt
ctxflow-1.5.dist-info/licenses/LICENSE
ctxflow-1.5.dist-info/RECORD
