Metadata-Version: 2.4
Name: ctxflow
Version: 1.5
Summary: ctxflow to keep you developing with ease
Project-URL: Documentation, https://github.com/Wacky404/ctx-container#readme
Project-URL: Issues, https://github.com/Wacky404/ctx-container/issues
Project-URL: Source, https://github.com/Wacky404/ctx-container
Author-email: Justin Flannery <juftin@juftin.com>, Wayne Cole <hi@waynecole.info>
License-Expression: MIT
License-File: LICENSE
Classifier: Development Status :: 4 - Beta
Classifier: Operating System :: OS Independent
Classifier: Programming Language :: Python
Classifier: Programming Language :: Python :: 3.8
Classifier: Programming Language :: Python :: 3.9
Classifier: Programming Language :: Python :: 3.10
Classifier: Programming Language :: Python :: 3.11
Classifier: Programming Language :: Python :: 3.12
Classifier: Programming Language :: Python :: Implementation :: CPython
Classifier: Programming Language :: Python :: Implementation :: PyPy
Requires-Python: <4,>=3.8.1
Requires-Dist: art~=6.1
Requires-Dist: click~=8.1.7
Requires-Dist: gitingest>=0.1.5
Requires-Dist: inquirerpy>=0.3.4
Requires-Dist: pandas<3,>2
Requires-Dist: pexpect>=4.9.0
Requires-Dist: pillow>=10.2.0
Requires-Dist: pip>=25.0.1
Requires-Dist: psutil>=7.0.0
Requires-Dist: pymupdf~=1.23.26
Requires-Dist: pyperclip~=1.8.2
Requires-Dist: requests>=2.32.4
Requires-Dist: rich-click~=1.7.4
Requires-Dist: rich-pixels~=2.2.0
Requires-Dist: rich~=13.7.1
Requires-Dist: textual-universal-directorytree~=1.5.0
Requires-Dist: textual==0.53.1
Requires-Dist: universal-pathlib~=0.2.2
Provides-Extra: all
Requires-Dist: pyarrow~=15.0.2; extra == 'all'
Requires-Dist: textual-universal-directorytree[remote]~=1.5.0; extra == 'all'
Provides-Extra: data
Requires-Dist: pyarrow~=15.0.2; extra == 'data'
Provides-Extra: parquet
Requires-Dist: pyarrow~=15.0.2; extra == 'parquet'
Provides-Extra: remote
Requires-Dist: textual-universal-directorytree[remote]~=1.5.0; extra == 'remote'
